[{"FIELD1": 1141, "key": "K2-165_d", "star_name": "K2-165", "planet_letter": "d", "discovery_method": "Transit", "pl_pnum": 3, "orbital_period": 14.101361, "semi_major": "NA", "orbital_eccentricity": "NA", "star_temp": 5185, "star_radius": 0.8, "planet_temp": "NA", "radius": 2.648, "discovery_year": 2018, "light_years": "NA"}, {"FIELD1": 2204, "key": "K2-165_c", "star_name": "K2-165", "planet_letter": "c", "discovery_method": "Transit", "pl_pnum": 3, "orbital_period": 4.382745, "semi_major": "NA", "orbital_eccentricity": "NA", "star_temp": 5185, "star_radius": 0.8, "planet_temp": "NA", "radius": 1.554, "discovery_year": 2018, "light_years": "NA"}, {"FIELD1": 2541, "key": "K2-165_b", "star_name": "K2-165", "planet_letter": "b", "discovery_method": "Transit", "pl_pnum": 3, "orbital_period": 2.354992, "semi_major": "NA", "orbital_eccentricity": "NA", "star_temp": 5185, "star_radius": 0.8, "planet_temp": "NA", "radius": 1.274, "discovery_year": 2018, "light_years": "NA"}]