[{"FIELD1": 326, "key": "Kepler-289_c", "star_name": "Kepler-289", "planet_letter": "c", "discovery_method": "Transit", "pl_pnum": 3, "orbital_period": 125.8518, "semi_major": 0.51, "orbital_eccentricity": "NA", "star_temp": 5990, "star_radius": 1, "planet_temp": "NA", "radius": 11.59, "discovery_year": 2014, "light_years": 2283.092}, {"FIELD1": 1102, "key": "Kepler-289_d", "star_name": "Kepler-289", "planet_letter": "d", "discovery_method": "Transit", "pl_pnum": 3, "orbital_period": 66.0634, "semi_major": 0.33, "orbital_eccentricity": "NA", "star_temp": 5990, "star_radius": 1, "planet_temp": "NA", "radius": 2.68, "discovery_year": 2014, "light_years": 2283.092}, {"FIELD1": 1615, "key": "Kepler-289_b", "star_name": "Kepler-289", "planet_letter": "b", "discovery_method": "Transit", "pl_pnum": 3, "orbital_period": 34.545, "semi_major": 0.21, "orbital_eccentricity": "NA", "star_temp": 5990, "star_radius": 1, "planet_temp": "NA", "radius": 2.15, "discovery_year": 2014, "light_years": 2283.092}]