[{"FIELD1": 2399, "key": "Kepler-186_d", "star_name": "Kepler-186", "planet_letter": "d", "discovery_method": "Transit", "pl_pnum": 5, "orbital_period": 13.342996, "semi_major": 0.0781, "orbital_eccentricity": "NA", "star_temp": 3755, "star_radius": 0.52, "planet_temp": "NA", "radius": 1.4, "discovery_year": 2014, "light_years": 560.98832}, {"FIELD1": 2547, "key": "Kepler-186_e", "star_name": "Kepler-186", "planet_letter": "e", "discovery_method": "Transit", "pl_pnum": 5, "orbital_period": 22.407704, "semi_major": 0.11, "orbital_eccentricity": "NA", "star_temp": 3755, "star_radius": 0.52, "planet_temp": "NA", "radius": 1.27, "discovery_year": 2014, "light_years": 560.98832}, {"FIELD1": 2571, "key": "Kepler-186_c", "star_name": "Kepler-186", "planet_letter": "c", "discovery_method": "Transit", "pl_pnum": 5, "orbital_period": 7.267302, "semi_major": 0.0451, "orbital_eccentricity": "NA", "star_temp": 3755, "star_radius": 0.52, "planet_temp": "NA", "radius": 1.25, "discovery_year": 2014, "light_years": 560.98832}, {"FIELD1": 2661, "key": "Kepler-186_f", "star_name": "Kepler-186", "planet_letter": "f", "discovery_method": "Transit", "pl_pnum": 5, "orbital_period": 129.9441, "semi_major": 0.432, "orbital_eccentricity": 0.04, "star_temp": 3755, "star_radius": 0.52, "planet_temp": "NA", "radius": 1.17, "discovery_year": 2014, "light_years": 560.98832}, {"FIELD1": 2744, "key": "Kepler-186_b", "star_name": "Kepler-186", "planet_letter": "b", "discovery_method": "Transit", "pl_pnum": 5, "orbital_period": 3.8867907, "semi_major": 0.0343, "orbital_eccentricity": "NA", "star_temp": 3755, "star_radius": 0.52, "planet_temp": "NA", "radius": 1.07, "discovery_year": 2014, "light_years": 560.98832}]