[{"FIELD1": 1786, "key": "Kepler-273_c", "star_name": "Kepler-273", "planet_letter": "c", "discovery_method": "Transit", "pl_pnum": 2, "orbital_period": 8.014927, "semi_major": 0.073, "orbital_eccentricity": "NA", "star_temp": 5626, "star_radius": 0.81, "planet_temp": "NA", "radius": 1.98, "discovery_year": 2014, "light_years": "NA"}, {"FIELD1": 2277, "key": "Kepler-273_b", "star_name": "Kepler-273", "planet_letter": "b", "discovery_method": "Transit", "pl_pnum": 2, "orbital_period": 2.936532, "semi_major": 0.037, "orbital_eccentricity": "NA", "star_temp": 5626, "star_radius": 0.81, "planet_temp": "NA", "radius": 1.5, "discovery_year": 2014, "light_years": "NA"}]